{"cars": [{"player": false, "position": 10, "length": 2, "id": "0", "orientation": "vertical"}, {"player": false, "position": 11, "length": 2, "id": "6", "orientation": "vertical"}, {"player": false, "position": 1, "length": 3, "id": "1", "orientation": "horizontal"}, {"player": false, "position": 4, "length": 2, "id": "3", "orientation": "horizontal"}, {"player": false, "position": 27, "length": 3, "id": "2", "orientation": "horizontal"}, {"player": false, "position": 21, "length": 2, "id": "5", "orientation": "horizontal"}, {"player": false, "position": 19, "length": 2, "id": "4", "orientation": "horizontal"}, {"player": false, "position": 7, "length": 3, "id": "7", "orientation": "horizontal"}, {"player": true, "position": 13, "length": 2, "id": "r", "orientation": "horizontal"}], "id": "prb17576"}